Compiled from "TestMain.java"
public class cn.stylefeng.guns.system.TestMain {
  public cn.stylefeng.guns.system.TestMain();
    Code:
       0: aload_0
       1: invokespecial #1                  // Method java/lang/Object."<init>":()V
       4: return

  public int getCount();
    Code:
       0: iconst_1
       1: istore_1
       2: iconst_2
       3: istore_2
       4: iload_1
       5: iload_2
       6: iadd
       7: ireturn

  public static void main(java.lang.String[]);
    Code:
       0: new           #2                  // class cn/stylefeng/guns/system/TestMain
       3: dup
       4: invokespecial #3                  // Method "<init>":()V
       7: astore_1
       8: aload_1
       9: invokevirtual #4                  // Method getCount:()I
      12: pop
      13: return
}
